{
  "collectionName": "components_cookie_banner_categories",
  "info": {
    "displayName": "categories",
    "icon": "align-left",
    "description": ""
  },
  "options": {},
  "attributes": {
    "heading": {
      "type": "string"
    },
    "description": {
      "type": "richtext"
    },
    "tabLabel": {
      "type": "string"
    },
    "alwaysActive": {
      "type": "boolean",
      "default": false
    },
    "alwaysActiveText": {
      "type": "string"
    },
    "hasSwitch": {
      "type": "boolean",
      "default": true
    }
  }
}
